vectorops/__init__.py
vectorops/geoduck.py
vectorops/storage.py
vectorops/utils.py
vectorops-0.1.1.dist-info/METADATA
vectorops-0.1.1.dist-info/WHEEL
vectorops-0.1.1.dist-info/top_level.txt
vectorops-0.1.1.dist-info/RECORD
