Metadata-Version: 2.2
Name: vectorops
Version: 0.1.1
Summary: A package for creating and managing datacubes for coastal resilience analysis.
Author-email: Will Gislason <gislawill@gmail.com>
License: MIT
Classifier: Programming Language :: Python :: 3
Classifier: License :: OSI Approved :: MIT License
Classifier: Operating System :: OS Independent
Requires-Python: <3.13,>=3.12
Requires-Dist: geospatial-analysis-environment>=0.1.11
Requires-Dist: coastal-resilience-utilities>=0.1.35
